pthelper/__init__.py
pthelper/trainer.py
pthelper/utils.py
pthelper-0.1.2.dist-info/LICENSE
pthelper-0.1.2.dist-info/METADATA
pthelper-0.1.2.dist-info/WHEEL
pthelper-0.1.2.dist-info/top_level.txt
pthelper-0.1.2.dist-info/RECORD
