Metadata-Version: 2.1
Name: pthelper
Version: 0.1.2
Summary: pthelper - boilerplate code for training, logging and evaluation in PyTorch.
Home-page: https://github.com/LakshyaMalhotra/pt_helper
Author: Lakshya Malhotra
Author-email: lakshya9009@gmail.com
License: MIT
Keywords: artificial-intelligence,deep-learning,pytorch,ml,torchinfo,model
Classifier: Topic :: Scientific/Engineering :: Artificial Intelligence
Classifier: License :: OSI Approved :: MIT License
Classifier: Operating System :: OS Independent
Classifier: Programming Language :: Python :: 3
Classifier: Programming Language :: Python :: 3.7
Classifier: Programming Language :: Python :: 3.8
Classifier: Programming Language :: Python :: 3.9
Classifier: Programming Language :: Python :: 3.10
Requires-Python: >=3.7
License-File: LICENSE
Requires-Dist: torch (>=1.10.1)
Requires-Dist: torchinfo (>=1.6.0)
Requires-Dist: numpy (>=1.22.0)
